__init__.py
ha_watchdog_libs/__init__.py
ha_watchdog_libs/watchdog_intervals.py
ha_watchdog_libs/watchdog_rules.py
ha_watchdog_libs/watchdog_script.py
ha_media_watchdog-0.2.0.dist-info/LICENSE
ha_media_watchdog-0.2.0.dist-info/METADATA
ha_media_watchdog-0.2.0.dist-info/WHEEL
ha_media_watchdog-0.2.0.dist-info/entry_points.txt
ha_media_watchdog-0.2.0.dist-info/top_level.txt
ha_media_watchdog-0.2.0.dist-info/RECORD
