Metadata-Version: 2.1
Name: ha-media-watchdog
Version: 0.2.0
Summary: Script to watch media in HmoeAssistant
License: MIT License
Project-URL: Homepage, https://github.com/rveachkc/ha-media-watchdog
Keywords: homeassistant
Classifier: Development Status :: 3 - Alpha
Classifier: Intended Audience :: Developers
Classifier: License :: OSI Approved :: MIT License
Classifier: Programming Language :: Python :: 3
Requires-Python: >=3.12
License-File: LICENSE
Requires-Dist: homeassistant-api>=4.2.2.post2
Requires-Dist: pyyaml>=6.0.2
Requires-Dist: rv-script-utils>=0.1.0
